argdispatch/__init__.py
argdispatch/py.typed
argdispatch-1.5.0.dist-info/licenses/AUTHORS
argdispatch-1.5.0.dist-info/licenses/LICENSE
argdispatch-1.5.0.dist-info/METADATA
argdispatch-1.5.0.dist-info/WHEEL
argdispatch-1.5.0.dist-info/top_level.txt
argdispatch-1.5.0.dist-info/zip-safe
argdispatch-1.5.0.dist-info/RECORD
