Metadata-Version: 2.4
Name: argdispatch
Version: 1.5.0
Summary: A drop-in replacement for `argparse` dispatching subcommand calls to functions, modules or binaries.
Home-page: http://framagit.org/spalax/argdispatch
Author: Louis Paternault
Author-email: spalax@gresille.org
License: GPL-3.0-or-later
Project-URL: Documentation, http://argdispatch.readthedocs.io
Project-URL: Source, https://framagit.org/spalax/argdispatch
Project-URL: Tracker, https://framagit.org/spalax/argdispatch/issues
Keywords: argparse argument commandline dispatch
Classifier: Development Status :: 5 - Production/Stable
Classifier: Intended Audience :: Developers
Classifier: Programming Language :: Python :: 3
Classifier: Programming Language :: Python :: 3.10
Classifier: Programming Language :: Python :: 3.11
Classifier: Programming Language :: Python :: 3.12
Classifier: Programming Language :: Python :: 3.13
Classifier: Programming Language :: Python :: 3.14
Classifier: Programming Language :: Python :: 3.15
Classifier: Topic :: Software Development :: User Interfaces
Requires-Python: <4,>=3.10
License-File: LICENSE
License-File: AUTHORS
Requires-Dist: setuptools
Dynamic: license-file
